geopfa/__init__.py
geopfa/_version.py
geopfa/data_readers.py
geopfa/datasets.py
geopfa/extrapolation.py
geopfa/layer_combination.py
geopfa/processing.py
geopfa/transformation.py
geopfa/geopfa2d/__init__.py
geopfa/geopfa2d/data_readers.py
geopfa/geopfa2d/layer_combination.py
geopfa/geopfa2d/plotters.py
geopfa/geopfa2d/processing.py
geopfa/geopfa2d/transformation.py
geopfa/geopfa2d/uncertainty.py
geopfa/geopfa3d/__init__.py
geopfa/geopfa3d/data_readers.py
geopfa/geopfa3d/layer_combination.py
geopfa/geopfa3d/plotters.py
geopfa/geopfa3d/processing.py
geopfa/geopfa3d/transformation.py
geopfa/io/__init__.py
geopfa/io/data_writers.py
geopfa-0.0.17.dist-info/METADATA
geopfa-0.0.17.dist-info/WHEEL
geopfa-0.0.17.dist-info/licenses/LICENSE
geopfa-0.0.17.dist-info/RECORD
