Metadata-Version: 2.4
Name: geoPFA
Version: 0.0.17
Summary: Geothermal Play Fairway Analysis
Project-URL: homepage, https://github.com/NREL/geoPFA
Project-URL: documentation, https://github.com/NREL/geoPFA
Project-URL: repository, https://github.com/NREL/geoPFA
Author-email: Nicole Taverna <Nicole.Taverna@nrel.gov>, Scott Mello <Scott.Mello@nrel.gov>, Guilherme Castelao <gpimenta@nrel.gov>, Dylan Hettinger <Dylan.Hettinger@nrel.gov>, Karthik Menon <Karthik.Menon@nrel.gov>, Emily Holt <Emily.Holt@nrel.gov>
Maintainer-email: Nicole Taverna <Nicole.Taverna@nrel.gov>
License-Expression: BSD-3-Clause
License-File: LICENSE
Keywords: PFA,geothermal
Classifier: Development Status :: 3 - Alpha
Classifier: Intended Audience :: Science/Research
Classifier: Natural Language :: English
Classifier: Programming Language :: Python :: 3.11
Classifier: Programming Language :: Python :: 3.12
Classifier: Programming Language :: Python :: 3.13
Classifier: Programming Language :: Python :: 3.14
Requires-Python: >=3.11
Requires-Dist: contextily>=1.6.2
Requires-Dist: geopandas>=0.14.4
Requires-Dist: gpy>=1.13.2
Requires-Dist: iapws>=1.5.4
Requires-Dist: matplotlib>=3.0
Requires-Dist: notebook
Requires-Dist: numpy>=1.21.6
Requires-Dist: pandas>=2.0
Requires-Dist: pathos>=0.3.3
Requires-Dist: pooch>=1.8
Requires-Dist: psutil>=6.1.0
Requires-Dist: pyarrow>=20.0
Requires-Dist: pykrige>=1.7
Requires-Dist: rasterio>=1.4.2
Requires-Dist: scipy>=1.11
Requires-Dist: shapely>=2.0.6
Requires-Dist: statsmodels>=0.14
Requires-Dist: tqdm>=4.67
Provides-Extra: dev
Requires-Dist: ipython>=8.29.0; extra == 'dev'
Requires-Dist: pre-commit>=4.0; extra == 'dev'
Requires-Dist: twine>=5.1; extra == 'dev'
Provides-Extra: doc
Requires-Dist: ghp-import>=2.1; extra == 'doc'
Requires-Dist: make>=0.1; extra == 'doc'
Requires-Dist: myst-parser>=3.0.1; extra == 'doc'
Requires-Dist: numpydoc>=1.6; extra == 'doc'
Requires-Dist: pandoc>=2.3; extra == 'doc'
Requires-Dist: pydata-sphinx-theme>=0.15; extra == 'doc'
Requires-Dist: sphinx-click>=5.1; extra == 'doc'
Requires-Dist: sphinx-copybutton>=0.5; extra == 'doc'
Requires-Dist: sphinx-tabs>=3.4; extra == 'doc'
Requires-Dist: sphinx<9,>=8.1.3; extra == 'doc'
Provides-Extra: test
Requires-Dist: hypothesis>=6.0; extra == 'test'
Requires-Dist: pytest-cases<4,>=3.8.6; extra == 'test'
Requires-Dist: pytest-cov>=3.0; extra == 'test'
Requires-Dist: pytest-profiling<2,>=1.7.0; extra == 'test'
Requires-Dist: pytest-xdist>=3.0; extra == 'test'
Requires-Dist: pytest>=7.0; extra == 'test'
Requires-Dist: tox>=4.0; extra == 'test'
